spaeti/__init__.py
spaeti/routes.py
spaeti/settings.py
spaeti/_django/__init__.py
spaeti/_django/settings.py
spaeti/_django/urls.py
spaeti/_django/wsgi.py
spaeti/static/logo.svg
spaeti/views/home.py
spaeti-0.0.dist-info/METADATA
spaeti-0.0.dist-info/WHEEL
spaeti-0.0.dist-info/top_level.txt
spaeti-0.0.dist-info/RECORD
