Metadata-Version: 2.1
Name: spaeti
Version: 0.0
Author-email: Florian Scherf <mail@florianscherf.de>
Requires-Python: >=3.7
Requires-Dist: lona (==1.13)
Requires-Dist: lona-picocss (==0.3.1)
Requires-Dist: aiohttp-wsgi (==0.10.0)
Requires-Dist: django (<3.3,>=3.2)
Provides-Extra: dev
Requires-Dist: mypy (==1.3.0) ; extra == 'dev'
Requires-Dist: isort (==5.12.0) ; extra == 'dev'
Requires-Dist: tox ; extra == 'dev'
Requires-Dist: coverage ; extra == 'dev'
Requires-Dist: pytest (==7.3.1) ; extra == 'dev'
Requires-Dist: build ; extra == 'dev'
Requires-Dist: twine ; extra == 'dev'
